asyncmodules/__init__.py
asyncmodules/cmdqueue.py
asyncmodules/configuration.py
asyncmodules/eventloop.py
asyncmodules/gpiod_mock.py
asyncmodules/metadata.py
asyncmodules/module.py
asyncmodules/module_gpiod.py
asyncmodules/module_threaded.py
asyncmodules/modulemanager.py
examples/cherrypy_example.py
examples/controller_example.py
examples/exception_example.py
examples/gpiod_example.py
examples/simple_example.py
examples/todo_filereader.py
examples/templates/base.html
examples/templates/index.html
examples/templates/login.html
examples/templates/part_header.html
examples/webroot/static/favicon.ico
examples/webroot/static/logo.png
examples/webroot/static/styles.css
asyncmodule-0.1.0.dist-info/LICENSE
asyncmodule-0.1.0.dist-info/METADATA
asyncmodule-0.1.0.dist-info/WHEEL
asyncmodule-0.1.0.dist-info/entry_points.txt
asyncmodule-0.1.0.dist-info/top_level.txt
asyncmodule-0.1.0.dist-info/RECORD
