Metadata-Version: 2.2
Name: asyncmodule
Version: 0.1.0
Summary: simplistic asyncio-based framework for loosely coupling application modules that can interact synchronously and asynchronously (event queue)
Home-page: https://www.github.com/towalink/asyncmodules
Author: Dirk Henrici
Author-email: towalink.asyncmodules@henrici.name
Project-URL: Project homepage, https://www.github.com/towalink/asyncmodules
Project-URL: Repository, https://www.github.com/towalink/asyncmodules
Project-URL: PyPi, https://pypi.org/project/asyncmodules/
Keywords: event-driven asynchronous asyncio messaging
Classifier: Programming Language :: Python
Classifier: Programming Language :: Python :: 3
Classifier: License :: OSI Approved :: GNU Affero General Public License v3 or later (AGPLv3+)
Classifier: Operating System :: POSIX :: Linux
Classifier: Development Status :: 3 - Alpha
Classifier: Intended Audience :: Developers
Classifier: Intended Audience :: Information Technology
Requires-Python: >=3.8
License-File: LICENSE
Requires-Dist: pyyaml
Provides-Extra: extra-feature
Requires-Dist: cherrypy; extra == "extra-feature"
Requires-Dist: jinja2; extra == "extra-feature"
Dynamic: author
Dynamic: author-email
Dynamic: classifier
Dynamic: description
Dynamic: description-content-type
Dynamic: home-page
Dynamic: keywords
Dynamic: project-url
Dynamic: provides-extra
Dynamic: requires-dist
Dynamic: requires-python
Dynamic: summary
